{
  "kind": "collectionType",
  "collectionName": "artists",
  "info": {
    "name": "artist",
    "description": ""
  },
  "options": {
    "increments": true,
    "timestamps": true,
    "draftAndPublish": true
  },
  "pluginOptions": {},
  "attributes": {
    "artisticName": {
      "type": "string"
    },
    "city": {
      "type": "string"
    },
    "links": {
      "type": "component",
      "repeatable": false,
      "component": "links.links"
    },
    "minibio": {
      "type": "richtext"
    },
    "VideoPresentation": {
      "type": "string"
    }
  }
}
